gerador_posts/__init__.py
gerador_posts/__main__.py
gerador_posts/configuracao.py
gerador_posts/gerador_posts.py
gerador_posts/tratar_dados.py
gerador_posts-0.1.4.dist-info/LICENSE
gerador_posts-0.1.4.dist-info/METADATA
gerador_posts-0.1.4.dist-info/WHEEL
gerador_posts-0.1.4.dist-info/entry_points.txt
gerador_posts-0.1.4.dist-info/top_level.txt
gerador_posts-0.1.4.dist-info/RECORD
