Metadata-Version: 2.1
Name: gerador-posts
Version: 0.1.4
Summary: Gerador de posts baseado em templates e arquivos de dados (csv e yaml).
Home-page: https://github.com/cecivieira/gerador-posts
Author: Ana Cecília Vieira
Author-email: cecivieira@gmail.com
License: MIT
Keywords: jinja2,yaml,templates
Platform: UNKNOWN
Requires-Python: >=3.10.6
License-File: LICENSE
Requires-Dist: Jinja2 (==3.1.2)
Requires-Dist: MarkupSafe (==2.1.2)
Requires-Dist: PyYAML (==6.0)
